wqrfproxy/__init__.py
wqrfproxy/mitm_catch.py
wqrfproxy/test.py
wqrfproxy/wqrfproxy.py
wqrfproxy-1.0.dist-info/METADATA
wqrfproxy-1.0.dist-info/WHEEL
wqrfproxy-1.0.dist-info/top_level.txt
wqrfproxy-1.0.dist-info/RECORD
