Metadata-Version: 2.1
Name: wqrfproxy
Version: 1.0
Summary: to catch the api from device
Home-page: https://github.com/Woqurefan/wqrfproxy
Author: wqrf
Author-email: 1074321997@qq.com
License: MIT
Keywords: wqrf
Platform: UNKNOWN
